Workbook

Sheet 1 Zusammenfassung
A1: Vereine als zweites Standbein
A2: Coach Grid · Entscheidungsgrundlage · Stand 29.07.2026. Blau = Eingabe, alles andere rechnet sich daraus.
A4: Die Idee in drei Sätzen
A5: Heute verkaufen wir einzeln: ein Coach zahlt CHF 399 im Jahr. Ein Verein hat 10–40 Coaches auf einen Schlag.
A6: Wir verkaufen dem Verein ein Paket für alle seine Coaches — ein Vertrag, eine Rechnung, ein Ansprechpartner.
A7: Der Verein bekommt Sichtbarkeit und ein Dashboard; die Anfrage geht weiterhin an den Coach. Die Plattform bleibt eine Coach-Plattform.
A9: Was dabei herausschaut (3 Jahre kumuliert)
A10: Szenario | B10: Neukunden J1 | C10: ARR Jahr 1 | D10: ARR Jahr 3 | E10: Kumuliert 3 Jahre | F10: Was dafür wahr sein muss
A11: Vorsichtig | B11: ='4 Szenarien'!D6 | C11: ='4 Szenarien'!D16 | D11: ='4 Szenarien'!D20 | E11: ='4 Szenarien'!D21 | F11: Wir schreiben die Liste an, wenige antworten, wir landen kleine Vereine.
A12: Realistisch | B12: ='4 Szenarien'!E6 | C12: ='4 Szenarien'!E16 | D12: ='4 Szenarien'!E20 | E12: ='4 Szenarien'!E21 | F12: Warme Ansprache statt Kaltmail, Fokus auf Golf und grosse Tennisclubs, 2 Referenzkunden.
A13: Optimistisch | B13: ='4 Szenarien'!F6 | C13: ='4 Szenarien'!F16 | D13: ='4 Szenarien'!F20 | E13: ='4 Szenarien'!F21 | F13: Ein Verband oder ein Referenzclub öffnet die Tür, Empfehlungen tragen den Rest.
A15: Die drei Punkte, die vor dem ersten Anruf entschieden sein müssen
A16: Nr. | B16: Befund | F16: Begründung
A17: 1 | B17: Der 10k-Preis kippt unter 25 Coaches | F17: CHF 10'000 geteilt durch CHF 399 sind 25 Coaches. Ein Verein mit 15 Coaches zahlt beim 10k-Deal das 1.7-fache dessen, was seine Coaches einzeln zahlen würden — das rechnet der erste Vereinspräsident in dreissig Sekunden nach. Darum Staffelpreise nach Coach-Zahl (Blatt 2).
A18: 2 | B18: Wenige grosse Vereine schlagen viele kleine | F18: 20 grosse Vereine à CHF 9'900 bringen gleich viel wie 200 kleine à CHF 1'000 — bei einem Zehntel Vertriebsaufwand und einem Zehntel Support. Zuerst Golf, grosse Tennisclubs und Eishockey.
A19: 3 | B19: Die Anfrage muss beim Coach landen | F19: Leiten wir Anfragen an die Vereinsadresse um, wird aus einer Coach-Plattform ein Vereinsverzeichnis. Der Verein bekommt Sichtbarkeit, Dashboard und Kopie jeder Anfrage — die Anfrage selbst geht an den Coach. Details und Vertragsklauseln auf Blatt 6.
A21: Empfehlung
A22: Pilot mit 50 Vereinen aus der bestehenden Kontaktliste (Golf und grosse Tennisclubs zuerst), Staffelpreis statt Einheitspreis, drei Referenzkunden zu Sonderkonditionen, Anfrage bleibt beim Coach. Entscheidung nach 90 Tagen anhand der Abschlussquote — Fahrplan auf Blatt 7.

Sheet 2 Preismodell
A1: Preismodell
A2: Der Vereinspreis muss unter der Summe der Einzelpreise liegen — sonst ist er nicht verhandelbar.
A4: Heutiger Einzelpreis pro Coach und Jahr | B4: 399 | C4: ← Eingabe
A6: Staffelpreise nach Anzahl Coaches
A7: Stufe | B7: Coaches ab | C7: Coaches bis | D7: Jahrespreis | E7: Preis pro Coach | F7: Rabatt vs. Einzel | G7: Monatspreis | H7: Ersparnis bei Jahreszahlung
A8: S – kleiner Verein | B8: 1 | C8: 10 | D8: 2490 | E8: =D8/((B8+C8)/2) | F8: =E8/$B$4-1 | G8: 249 | H8: =G8*12-D8
A9: M – mittlerer Verein | B9: 11 | C9: 25 | D9: 4900 | E9: =D9/((B9+C9)/2) | F9: =E9/$B$4-1 | G9: 490 | H9: =G9*12-D9
A10: L – grosser Verein | B10: 26 | C10: 40 | D10: 9900 | E10: =D10/((B10+C10)/2) | F10: =E10/$B$4-1 | G10: 990 | H10: =G10*12-D10
A11: XL – Grossverein | B11: 41 | C11: 80 | D11: 14900 | E11: =D11/((B11+C11)/2) | F11: =E11/$B$4-1 | G11: 1490 | H11: =G11*12-D11
A12: Der Monatspreis ist bewusst höher gerechnet: wer jährlich zahlt, spart sichtbar. Beim grossen Verein sind das CHF 1'980 — genau die Logik «CHF 990 im Monat oder CHF 9'900 im Jahr».
A14: Gegenprobe: Vereinspreis gegen die Summe der Einzelanmeldungen
A15: Coaches im Verein | B15: Summe Einzelpreise | C15: Vereinspreis L (10k-Idee) | D15: Differenz für den Verein | E15: Verhältnis | F15: Urteil
A16: 5 | B16: =A16*$B$4 | C16: =$D$10 | D16: =C16-B16 | E16: =C16/B16 | F16: Verein zahlt drauf
A17: 10 | B17: =A17*$B$4 | C17: =$D$10 | D17: =C17-B17 | E17: =C17/B17 | F17: Verein zahlt drauf
A18: 15 | B18: =A18*$B$4 | C18: =$D$10 | D18: =C18-B18 | E18: =C18/B18 | F18: Verein zahlt drauf
A19: 20 | B19: =A19*$B$4 | C19: =$D$10 | D19: =C19-B19 | E19: =C19/B19 | F19: Verein zahlt drauf
A20: 25 | B20: =A20*$B$4 | C20: =$D$10 | D20: =C20-B20 | E20: =C20/B20 | F20: Break-even (Differenz CHF 25)
A21: 30 | B21: =A21*$B$4 | C21: =$D$10 | D21: =C21-B21 | E21: =C21/B21 | F21: Verein spart
A22: 40 | B22: =A22*$B$4 | C22: =$D$10 | D22: =C22-B22 | E22: =C22/B22 | F22: Verein spart
A23: 50 | B23: =A23*$B$4 | C23: =$D$10 | D23: =C23-B23 | E23: =C23/B23 | F23: Verein spart
A25: Break-even liegt bei CHF 10'000 / CHF 399 = 25 Coaches. Da die meisten Vereine 10–20 Coaches haben, ist der Einheitspreis von 10k für die Mehrheit ein Argument gegen uns. Mit der Staffel bleibt jede Stufe unter der Einzelsumme und der Verein spart sichtbar.

Sheet 3 Zielmarkt
A1: Zielmarkt
A2: Basis ist unsere eigene Kontaktliste (414 Einträge mit Telefon, Mail und Adresse) — nicht der Gesamtmarkt.
A4: Sportart | B4: In unserer Liste | C4: Markt CH gesamt | D4: Ø Coaches pro Verein | E4: Passende Stufe | F4: Preis pro Jahr | G4: Potenzial bei 100 % | H4: Warum diese Priorität
A5: Golf | B5: 103 | C5: 100 | D5: 6 | E5: S | F5: =INDEX('2 Preismodell'!$D$8:$D$11,1) | G5: =B5*F5 | H5: Höchste Zahlungskraft: eigener Platz, Geschäftsführung, Marketingbudget. Wenige Pros, darum Stufe S.
A6: Tennis | B6: 99 | C6: 900 | D6: 12 | E6: M | F6: =INDEX('2 Preismodell'!$D$8:$D$11,2) | G6: =B6*F6 | H6: Grösste Zahl an Clubs mit eigener Anlage. Herz der Zielgruppe.
A7: Schwimmen | B7: 180 | C7: 175 | D7: 20 | E7: M | F7: =INDEX('2 Preismodell'!$D$8:$D$11,2) | G7: =B7*F7 | H7: Viele Trainer pro Verein und laufendes Kursgeschäft — dort wird ohnehin gesucht.
A8: Reiten & Eishockey | B8: 32 | C8: 450 | D8: 25 | E8: M | F8: =INDEX('2 Preismodell'!$D$8:$D$11,2) | G8: =B8*F8 | H8: Eishockey mit grossem Nachwuchsstab; Reitbetriebe meist kommerziell geführt und entscheiden schnell.
A9: Total | B9: =SUM(B5:B8) | C9: =SUM(C5:C8) | G9: =SUM(G5:G8) | H9: Theoretische Obergrenze, wenn jeder Verein der Liste zahlt. Nie die Planzahl.
A11: Vom Kontakt zum Kunden
A12: Stufe | B12: Vorsichtig | C12: Realistisch | D12: Optimistisch | H12: Bemerkung
A13: Vereine angeschrieben | B13: ='4 Szenarien'!D4 | C13: ='4 Szenarien'!E4 | D13: ='4 Szenarien'!F4 | H13: Aus der Liste, mit Name des Ansprechpartners.
A14: davon antworten | B14: ='4 Szenarien'!D4*'4 Szenarien'!D5 | C14: ='4 Szenarien'!E4*'4 Szenarien'!E5 | D14: ='4 Szenarien'!F4*'4 Szenarien'!F5 | H14: Antwortquote steht auf Blatt 4 und ist änderbar.
A15: davon schliessen ab | B15: ='4 Szenarien'!D6 | C15: ='4 Szenarien'!E6 | D15: ='4 Szenarien'!F6 | H15: Kunden im ersten Jahr.
A16: Abschlussquote gesamt | B16: =B15/B13 | C16: =C15/C13 | D16: =D15/D13 | H16: Anteil der angeschriebenen Vereine, der unterschreibt.

Sheet 4 Szenarien
A1: Szenarien über drei Jahre
A2: Blau ist Eingabe. Alles darunter rechnet sich daraus.
A3: Treiber | D3: Vorsichtig | E3: Realistisch | F3: Optimistisch | H3: Bemerkung
A4: Vereine angeschrieben (Jahr 1) | D4: 200 | E4: 350 | F4: 414 | H4: Die Liste hat 414 Einträge mit Kontaktdaten.
A5: Antwortquote | D5: 0.12 | E5: 0.2 | F5: 0.3 | H5: Kaltmail an Vereine liegt erfahrungsgemäss bei 10–20 %; mit Telefon-Nachfassen höher. Annahme.
A6: Abschlüsse Jahr 1 | D6: =ROUND(D4*D5*D7,0) | E6: =ROUND(E4*E5*E7,0) | F6: =ROUND(F4*F5*F7,0) | H6: Angeschrieben × Antwortquote × Abschluss aus Antwort, auf ganze Vereine gerundet.
A7: Abschluss aus Antwort | D7: 0.08 | E7: 0.15 | F7: 0.25 | H7: Annahme, im Pilot zu messen.
A8: Ø Jahrespreis pro Verein | D8: 2490 | E8: 4900 | F8: 6900 | H8: Vorsichtig = nur Stufe S, realistisch = Stufe M, optimistisch = Mischung M und L.
A9: Verlängerungsquote pro Jahr | D9: 0.75 | E9: 0.85 | F9: 0.9 | H9: Vertragslaufzeit 24 Monate, danach jährliche Verlängerung.
A10: Neue Vereine Jahr 2 | D10: 8 | E10: 20 | F10: 45 | H10: Empfehlungen und zweite Welle.
A11: Neue Vereine Jahr 3 | D11: 10 | E11: 30 | F11: 70 | H11: Ab hier trägt die Referenzliste.
A13: Ergebnis
A14: Kennzahl | D14: Vorsichtig | E14: Realistisch | F14: Optimistisch | H14: Bemerkung
A15: Kunden Ende Jahr 1 | D15: =D6 | E15: =E6 | F15: =F6
A16: ARR Jahr 1 | D16: =D15*D8 | E16: =E15*E8 | F16: =F15*F8 | H16: Wiederkehrender Jahresumsatz.
A17: Kunden Ende Jahr 2 | D17: =ROUND(D15*D9+D10,0) | E17: =ROUND(E15*E9+E10,0) | F17: =ROUND(F15*F9+F10,0) | H17: Bestand nach Kündigungen plus neue.
A18: ARR Jahr 2 | D18: =D17*D8 | E18: =E17*E8 | F18: =F17*F8
A19: Kunden Ende Jahr 3 | D19: =ROUND(D17*D9+D11,0) | E19: =ROUND(E17*E9+E11,0) | F19: =ROUND(F17*F9+F11,0)
A20: ARR Jahr 3 | D20: =D19*D8 | E20: =E19*E8 | F20: =F19*F8
A21: Umsatz 3 Jahre kumuliert | D21: =D16+D18+D20 | E21: =E16+E18+E20 | F21: =F16+F18+F20 | H21: Summe der drei Jahresumsätze.
A23: Gegenprobe zu den Zahlen aus dem Chat
A24: Behauptung | D24: Rechnung | E24: Nötige Abschlussquote | F24: Urteil | H24: Kommentar
A25: «200 Vereine à CHF 1'000 über 3 Jahre = CHF 600'000» | D25: =200*1000*3 | E25: =200/F4 | F25: Möglich, aber teuer erkauft | H25: Rechnerisch korrekt. Es braucht aber 200 Abschlüsse — knapp die Hälfte unserer ganzen Liste. Und CHF 1'000 sind 2.5 Coaches zum Einzelpreis: viel Aufwand für wenig Ertrag pro Kunde.
A26: «10 Vereine à CHF 10'000 = CHF 100'000» | D26: =10*10000 | E26: =10/F4 | F26: Der bessere Weg | H26: Nur 10 Abschlüsse nötig — 2 % der Liste. Aber nur bei Vereinen ab 25 Coaches verhandelbar (Blatt 2). Realistisch sind das die grössten Eishockey- und Tennisclubs.
A29: Diagrammdaten (verweisen auf die Ergebnisse oben)
D30: Vorsichtig | E30: Realistisch | F30: Optimistisch
A31: ARR Jahr 1 | D31: =D16 | E31: =E16 | F31: =F16
A32: ARR Jahr 2 | D32: =D18 | E32: =E18 | F32: =F18
A33: ARR Jahr 3 | D33: =D20 | E33: =E20 | F33: =F20

Sheet 5 Sensitivität
A1: Sensitivität
A2: Wiederkehrender Jahresumsatz je Kombination aus Preis und Anzahl Kunden.
A4: Kunden ↓ / Preis → | B4: 1000 | C4: 2490 | D4: 4900 | E4: 6900 | F4: 9900 | G4: 14900
A5: 5 | B5: =$A5*B$4 | C5: =$A5*C$4 | D5: =$A5*D$4 | E5: =$A5*E$4 | F5: =$A5*F$4 | G5: =$A5*G$4
A6: 10 | B6: =$A6*B$4 | C6: =$A6*C$4 | D6: =$A6*D$4 | E6: =$A6*E$4 | F6: =$A6*F$4 | G6: =$A6*G$4
A7: 20 | B7: =$A7*B$4 | C7: =$A7*C$4 | D7: =$A7*D$4 | E7: =$A7*E$4 | F7: =$A7*F$4 | G7: =$A7*G$4
A8: 30 | B8: =$A8*B$4 | C8: =$A8*C$4 | D8: =$A8*D$4 | E8: =$A8*E$4 | F8: =$A8*F$4 | G8: =$A8*G$4
A9: 50 | B9: =$A9*B$4 | C9: =$A9*C$4 | D9: =$A9*D$4 | E9: =$A9*E$4 | F9: =$A9*F$4 | G9: =$A9*G$4
A10: 80 | B10: =$A10*B$4 | C10: =$A10*C$4 | D10: =$A10*D$4 | E10: =$A10*E$4 | F10: =$A10*F$4 | G10: =$A10*G$4
A11: 120 | B11: =$A11*B$4 | C11: =$A11*C$4 | D11: =$A11*D$4 | E11: =$A11*E$4 | F11: =$A11*F$4 | G11: =$A11*G$4
A12: 200 | B12: =$A12*B$4 | C12: =$A12*C$4 | D12: =$A12*D$4 | E12: =$A12*E$4 | F12: =$A12*F$4 | G12: =$A12*G$4
A14: Grün ab CHF 200'000 wiederkehrend, orange ab CHF 100'000. Die gleiche Zelle erreicht man auf zwei Wegen: 200 kleine Kunden zu CHF 1'000 oder 20 grosse zu CHF 9'900. Beides ergibt rund CHF 200'000 — der zweite Weg kostet ein Zehntel des Vertriebsaufwands. Das ist das eigentliche Argument für die Staffel.

Sheet 6 Konflikt & Lösung
A1: Der Zielkonflikt — und wie wir ihn auflösen
A2: Der Verein zahlt, weil er etwas davon hat. Die Plattform lebt davon, dass es um den Coach geht.
A4: Das Problem in einem Satz
A5: Ein Verein zahlt nur, wenn er den Nutzen sieht — der Nutzen ist die Anfrage. Leiten wir Anfragen an die Vereinsadresse, wird aus der Coach-Plattform ein Vereinsverzeichnis, und die Coaches verlieren den Grund, bei uns zu sein.
A7: Modell | B7: Wie es läuft | C7: Spricht dafür | D7: Spricht dagegen | E7: Urteil
A8: A — Anfrage an den Verein | B8: Coach-Profile bleiben sichtbar, aber jeder Kontaktbutton führt zur Vereinsadresse. | C8: Für den Verein die einfachste Zusage: er behält die Kundenbeziehung vollständig. | D8: Bricht das Versprechen der Plattform. Coaches werden zu Karteikarten und wandern ab. Der Kunde erwartet den Coach, den er angeschrieben hat, und bekommt eine Zentrale. | E8: Nicht empfohlen
A9: B — Anfrage nur an den Coach | B9: Alles bleibt wie heute, der Verein zahlt für Sichtbarkeit und sein Logo auf den Profilen. | C9: Philosophie bleibt unangetastet, kein Bruch im Produkt. | D9: Der Verein fragt zu Recht: wofür zahle ich? Ohne sichtbaren Rücklauf keine Verlängerung. | E9: Zu wenig für den Verein
A10: C — Anfrage an den Coach, Verein in Kopie | B10: Die Anfrage geht an den Coach. Der Verein erhält automatisch eine Kopie und sieht im Dashboard alle Anfragen, Buchungen und Auslastung seiner Coaches. | C10: Der Coach bleibt der Ansprechpartner — Versprechen gehalten. Der Verein sieht schwarz auf weiss, was das Abo bringt, und behält die Kontrolle über seine Coaches. | D10: Etwas Entwicklungsaufwand: Vereinskonto, Dashboard, Kopie-Zustellung. | E10: Empfehlung
A12: Die vier Einwände, die im Gespräch garantiert kommen
A13: Einwand | B13: Antwort | C13: Regelung im Vertrag
A14: «Dann melden sich unsere Coaches einfach privat an und wir zahlen umsonst.» | B14: Solange der Verein zahlt, läuft der Coach über den Vereinscode. Ein zweites Privatprofil ist nur mit Freigabe des Vereins möglich. | C14: Vereinscodes pro Coach; keine Doppellistung ohne Freigabe; Code erlischt beim Vereinsaustritt.
A15: «Privatlektionen sind billiger, dann bucht niemand mehr über uns.» | B15: In Tennis, Schwimmen und Ski ist die Privatlektion regelmässig teurer als das Vereinsangebot — sie ist die Zusatzleistung, nicht die günstigere Alternative. | C15: Preisuntergrenze: Privatlektionen eines Vereinscoaches liegen mindestens auf Vereinsniveau.
A16: «Was, wenn ein Coach den Verein verlässt?» | B16: Sein Zugang wird deaktiviert, das Profil verschwindet aus dem Vereinspaket. Der Verein zahlt nie für jemanden, der nicht mehr da ist. | C16: Codes monatlich abrechenbar; Deaktivierung innert 5 Werktagen; Meldepflicht des Vereins.
A17: «Könnt ihr uns Kunden garantieren?» | B17: Nein — und das sagen wir offen. Wir erhöhen die Wahrscheinlichkeit, gefunden zu werden, weil wir Marketing und Sichtbarkeit übernehmen. Eine Zusage auf Kundenzahlen macht niemand seriös. | C17: Keine Erfolgsgarantie im Vertrag. Stattdessen: Reporting und Ausstieg nach 24 Monaten.

Sheet 7 Fahrplan 90 Tage
A1: Fahrplan über 90 Tage
A2: Ziel: nach drei Monaten wissen wir, ob das Modell trägt — mit Zahlen statt Meinung.
A4: Zeitraum | B4: Schritt | C4: Was konkret passiert | D4: Verantwortlich | E4: Fertig wenn | F4: Messgrösse
A5: Woche 1–2 | B5: Angebot fertig machen | C5: Staffelpreise festlegen, Vertragsentwurf mit Codes und Preisuntergrenze, eine Seite für Vereine auf der Website. | D5: Robert / Navid | E5: Vertrag und Preisliste stehen | F5: —
A6: Woche 2 | B6: Zielliste schneiden | C6: Aus den 414 Kontakten die 50 aussichtsreichsten ziehen: Golf und grosse Tennisclubs mit Mailadresse. | D6: Navid | E6: Liste mit 50 Vereinen steht | F6: 50 Kontakte
A7: Woche 3–4 | B7: Erste Welle | C7: 50 Vereine anschreiben, nach 4 Tagen telefonisch nachfassen. Gleiche Botschaft wie bei Coaches: mehr Sichtbarkeit, keine Garantie. | D7: Navid | E7: 50 angeschrieben, 50 nachgefasst | F7: Antwortquote
A8: Woche 5–8 | B8: Gespräche führen | C8: Termine wahrnehmen, Blatt 2 und 6 als Gesprächsgrundlage nutzen, Einwände sauber beantworten. | D8: Robert | E8: mindestens 8 Termine | F8: Termine pro 50 Kontakte
A9: Woche 6–10 | B9: Drei Piloten gewinnen | C9: Drei Vereine zu Sonderkonditionen: erstes Jahr halber Preis gegen das Recht, sie als Referenz zu nennen. | D9: Robert / Navid | E9: 3 unterschriebene Verträge | F9: Abschlussquote
A10: Woche 9–12 | B10: Belegen und entscheiden | C10: Anfragen pro Pilotverein messen, eine Fallstudie schreiben, Preis fixieren oder Modell verwerfen. | D10: Navid | E10: Fallstudie liegt vor | F10: Anfragen pro Verein und Monat
A12: Abbruchkriterien — wann wir das Modell wieder einpacken
A13: • Unter 8 % Antwortquote auf 50 saubere Kontakte: die Botschaft stimmt nicht, nicht der Markt.
A14: • Null Abschlüsse nach 10 geführten Gesprächen: der Preis oder das Modell trägt nicht.
A15: • Weniger als 2 Anfragen pro Pilotverein und Monat: der Verein verlängert nicht, egal wie gut das Gespräch war.

Sheet 8 Annahmen & Quellen
A1: Annahmen und Quellen
A2: Was gemessen ist, was geschätzt ist, und woher es kommt.
A4: Annahme | B4: Wert | C4: Art | D4: Herkunft
A5: Einzelpreis pro Coach und Jahr | B5: CHF 399 | C5: gesetzt | D5: Von euch genannt (Chat vom 29.07.2026).
A6: Coaches pro Verein | B6: 10–20, teils 40+ | C6: eure Beobachtung | D6: Von euch genannt. Für Golf eher tief (3–8 Pros), für Eishockey und Schwimmen eher hoch — darum auf Blatt 3 pro Sportart änderbar.
A7: Kontaktierbare Vereine | B7: 414 | C7: gemessen | D7: Eigene Liste vom 28.07.2026: Golf 103, Tennis 99, Schwimmen 180, Reiten und Eishockey 32.
A8: Vereine im Markt CH | B8: rund 1'600 mit eigener Anlage | C8: recherchiert | D8: Swiss Tennis rund 900 Clubs, Swiss Golf über 90, Swiss Aquatics 175, Eishockey und Reitbetriebe geschätzt.
A9: Sportvereine CH gesamt | B9: 18'310 mit 2.2 Mio. Mitgliedschaften | C9: recherchiert | D9: Vereinsstudie 2022, Swiss Olympic.
A10: Ø Einnahmen eines Sportvereins | B10: CHF 69'000 pro Jahr | C10: recherchiert | D10: Observatorium Sport und Bewegung Schweiz. Wichtig fürs Preisgespräch: ein 10k-Abo wäre bei einem Durchschnittsverein 14 % des gesamten Jahresbudgets.
A11: Vereine ohne bezahlte Mitarbeitende | B11: 82 % | C11: recherchiert | D11: Vereinsstudie 2022. Deshalb Staffelpreise statt Einheitspreis.
A12: Antwortquote auf Kaltmail | B12: 12 / 20 / 30 % | C12: Annahme | D12: Erfahrungswert B2B mit telefonischem Nachfassen. Im Pilot zu messen, nicht belegt.
A13: Abschluss aus Antwort | B13: 8 / 15 / 25 % | C13: Annahme | D13: Erfahrungswert. Im Pilot zu messen, nicht belegt.
A14: Verlängerungsquote | B14: 75 / 85 / 90 % | C14: Annahme | D14: Bei 24 Monaten Laufzeit. Nicht belegt.
A17: Quellen
A18: Vereinsstudie 2022, Swiss Olympic | B18: https://www.swissolympic.ch/dam/jcr:e13bfb8d-92a6-41a3-89e4-b80d30c2d23c/Vereinsstudie%202022_DE_Web.pdf
A19: Vereinsfinanzen, Sportobservatorium | B19: https://www.sportobs.ch/inhalte/Indikatoren_PDF_neu/Ind_22_Sportobs.pdf
A20: Swiss Aquatics, Mitgliedvereine | B20: https://www.swiss-aquatics.ch/verband/mitglieder/alle-mitgliedvereine/
A21: Swiss Tennis | B21: https://www.swisstennis.ch/de/
A22: Swiss Golf | B22: https://www.swissgolf.ch/
A24: Alles in der Spalte «Annahme» ist noch nicht belegt. Diese vier Zahlen entscheiden über das ganze Modell — der 90-Tage-Pilot dient in erster Linie dazu, sie durch gemessene Werte zu ersetzen.
